Metadata-Version: 2.1
Name: rvs-palmvision
Version: 0.0.1
Summary: Machine Learning using Palmvision ! 
Author: Rohith Vijay R
Author-email: rohithvijayr6012@gmail.com
License: MIT
Keywords: Computervisiom,Machine Learning,handtracking,palmvision
Classifier: Development Status :: 3 - Alpha
Classifier: Intended Audience :: Developers
Classifier: Topic :: Software Development :: Build Tools
Classifier: License :: OSI Approved :: MIT License
Classifier: Programming Language :: Python :: 3.6
Classifier: Programming Language :: Python :: 3.8
Classifier: Programming Language :: Python :: 3.9
Classifier: Programming Language :: Python :: 3.10
Classifier: Programming Language :: Python :: 3.11
Classifier: Programming Language :: Python :: 3.12
License-File: LICENCE.txt
